pveagle/LICENSE
pveagle/__init__.py
pveagle/_eagle.py
pveagle/_factory.py
pveagle/_util.py
pveagle/lib/common/eagle_params.pv
pveagle/lib/linux/x86_64/libpv_eagle.so
pveagle/lib/mac/arm64/libpv_eagle.dylib
pveagle/lib/mac/x86_64/libpv_eagle.dylib
pveagle/lib/raspberry-pi/cortex-a53/libpv_eagle.so
pveagle/lib/raspberry-pi/cortex-a53-aarch64/libpv_eagle.so
pveagle/lib/raspberry-pi/cortex-a72/libpv_eagle.so
pveagle/lib/raspberry-pi/cortex-a72-aarch64/libpv_eagle.so
pveagle/lib/raspberry-pi/cortex-a76/libpv_eagle.so
pveagle/lib/raspberry-pi/cortex-a76-aarch64/libpv_eagle.so
pveagle/lib/windows/amd64/libpv_eagle.dll
pveagle/lib/windows/amd64/pv_ypu_impl_cuda.dll
pveagle/lib/windows/arm64/libpv_eagle.dll
pveagle-2.0.0.dist-info/METADATA
pveagle-2.0.0.dist-info/WHEEL
pveagle-2.0.0.dist-info/top_level.txt
pveagle-2.0.0.dist-info/RECORD
